MANIFEST.in
setup.py
porsche/__init__.py
porsche/__main__.py
porsche/media_processing.py
porsche.egg-info/PKG-INFO
porsche.egg-info/SOURCES.txt
porsche.egg-info/dependency_links.txt
porsche.egg-info/top_level.txt
porsche/face/__init__.py
porsche/face/face_cartoon.py
porsche/face/face_detector.py
porsche/face/segmentation.py
porsche/filters/__init__.py
porsche/filters/one_euro_filter.py
porsche/models/GlobalSkinSeg.onnx
porsche/models/HeadSeg.onnx
porsche/models/PortraitSeg.onnx
porsche/models/blazeface.onnx
porsche/models/blazeface_anchors.csv
porsche/models/default_lut.png
porsche/models/light_luminance_bs1_0831.onnx
porsche/models/student_gan_0902.onnx
porsche/models/student_gan_0902_dynamic_axes.onnx
porsche/scene/__init__.py
porsche/scene/classifier.py
porsche/utils/__init__.py
porsche/utils/army_knife.py
porsche/utils/img_utils.py
porsche/utils/plot.py
porsche/utils/tips.py