Metadata-Version: 1.0
Name: porsche
Version: 0.0.7
Summary: Collection of mess function...
Home-page: http://www.xxx.com
Author: edvardzeng
Author-email: edvard_hua@live.com
License: UNKNOWN
Platform: UNKNOWN
